picchick/__init__.py
picchick/__main__.py
picchick/cli.py
picchick/devices.py
picchick/hexfile.py
picchick/programmer/__init__.py
picchick/programmer/arduino_icsp.py
picchick/programmer/flipflop.py
picchick/programmer/picstick.py
picchick/programmer/programmer.py
picchick-0.4.1.dist-info/LICENSE
picchick-0.4.1.dist-info/METADATA
picchick-0.4.1.dist-info/WHEEL
picchick-0.4.1.dist-info/entry_points.txt
picchick-0.4.1.dist-info/top_level.txt
picchick-0.4.1.dist-info/RECORD
