Metadata-Version: 2.1
Name: picchick
Version: 0.4.1
Summary: A utility for programming and debugging microcontrollers.
Home-page: https://github.com/rex--/picchick
Author: Rex McKinnon
Author-email: 0xff@rexploits.com
License: University of Illinois/NCSA Open Source License
Classifier: Programming Language :: Python :: 3.9
Classifier: License :: OSI Approved :: University of Illinois/NCSA Open Source License
Requires-Python: >=3.9
License-File: LICENSE
Requires-Dist: pyserial
